{
    "data": {
        "news": [
            {
                "title": "Afghanistan bring back former Ireland allrounder John Mooney as fielding coach",
                "description": "John Mooney joins the Afghanistanteam ahead of the UAE tri-series starting August 29",
                "description_text": "John Mooney joins the Afghanistanteam ahead of the UAE tri-series starting August 29",
                "image_url": "https://p.imgci.com/db/PICTURES/CMS/288900/288957.6.jpg",
                "link": "https://www.espncricinfo.com/ci/content/story/1500513.html?ex_cid=OTC-RSS",
                "provider": {
                    "name": "Cricket news from ESPN Cricinfo.com",
                    "url": "https://www.espncricinfo.com/"
                },
                "updated": "2025-08-27T07:54:12"
            },
            {
                "title": "Afghanistan bring back former Ireland allrounder John Mooney as fielding coach",
                "description": "John Mooney joins the Afghanistanteam ahead of the UAE tri-series starting August 29",
                "description_text": "John Mooney joins the Afghanistanteam ahead of the UAE tri-series starting August 29",
                "image_url": "https://p.imgci.com/db/PICTURES/CMS/288900/288957.6.jpg",
                "link": "https://www.espncricinfo.com/ci/content/story/1500513.html?ex_cid=OTC-RSS",
                "provider": {
                    "name": "Cricket news from ESPN Cricinfo.com",
                    "url": "https://www.espncricinfo.com/"
                },
                "updated": "2025-08-27T07:54:12"
            },
            {
                "title": "Junaid Siddique comes back as UAE ring in the changes for T20 tri-series",
                "description": "Harshit Kaushik, Muhammad Farooq and Muhammad Jawadullah are the others to have come into the side for the T20Is against Afghanistan and Pakistan",
                "description_text": "Harshit Kaushik, Muhammad Farooq and Muhammad Jawadullah are the others to have come into the side for the T20Is against Afghanistan and Pakistan",
                "image_url": "https://p.imgci.com/db/PICTURES/CMS/353300/353324.6.jpg",
                "link": "https://www.espncricinfo.com/ci/content/story/1500512.html?ex_cid=OTC-RSS",
                "provider": {
                    "name": "Cricket news from ESPN Cricinfo.com",
                    "url": "https://www.espncricinfo.com/"
                },
                "updated": "2025-08-27T07:41:58"
            },
            {
                "title": "Junaid Siddique comes back as UAE ring in the changes for T20 tri-series",
                "description": "Harshit Kaushik, Muhammad Farooq and Muhammad Jawadullah are the others to have come into the side for the T20Is against Afghanistan and Pakistan",
                "description_text": "Harshit Kaushik, Muhammad Farooq and Muhammad Jawadullah are the others to have come into the side for the T20Is against Afghanistan and Pakistan",
                "image_url": "https://p.imgci.com/db/PICTURES/CMS/353300/353324.6.jpg",
                "link": "https://www.espncricinfo.com/ci/content/story/1500512.html?ex_cid=OTC-RSS",
                "provider": {
                    "name": "Cricket news from ESPN Cricinfo.com",
                    "url": "https://www.espncricinfo.com/"
                },
                "updated": "2025-08-27T07:41:58"
            },
            {
                "title": "R Ashwin brings curtain down on 'my time as an IPL cricketer'",
                "description": "\"My time as an explorer of the game around various leagues begins today,\" R Ashwin says",
                "description_text": "\"My time as an explorer of the game around various leagues begins today,\" R Ashwin says",
                "image_url": "https://p.imgci.com/db/PICTURES/CMS/403100/403169.6.jpg",
                "link": "https://www.espncricinfo.com/ci/content/story/1500505.html?ex_cid=OTC-RSS",
                "provider": {
                    "name": "Cricket news from ESPN Cricinfo.com",
                    "url": "https://www.espncricinfo.com/"
                },
                "updated": "2025-08-27T05:45:53"
            },
            {
                "title": "R Ashwin brings curtain down on 'my time as an IPL cricketer'",
                "description": "\"My time as an explorer of the game around various leagues begins today,\" R Ashwin says",
                "description_text": "\"My time as an explorer of the game around various leagues begins today,\" R Ashwin says",
                "image_url": "https://p.imgci.com/db/PICTURES/CMS/403100/403169.6.jpg",
                "link": "https://www.espncricinfo.com/ci/content/story/1500505.html?ex_cid=OTC-RSS",
                "provider": {
                    "name": "Cricket news from ESPN Cricinfo.com",
                    "url": "https://www.espncricinfo.com/"
                },
                "updated": "2025-08-27T05:45:53"
            },
            {
                "title": "Auguste's 73 off 35 trumps Shepherd's 73* off 34 to lift St Lucia Kings to second",
                "description": "Oshane Thomas concedes 33 runs in a ten-ball over (the 15th of the Amazon Warriors innings) - the most expensive figures by a St Lucia Kings bowler in the CPL",
                "description_text": "Oshane Thomas concedes 33 runs in a ten-ball over (the 15th of the Amazon Warriors innings) - the most expensive figures by a St Lucia Kings bowler in the CPL",
                "image_url": "https://p.imgci.com/db/PICTURES/CMS/405400/405458.6.jpg",
                "link": "https://www.espncricinfo.com/ci/content/story/1500502.html?ex_cid=OTC-RSS",
                "provider": {
                    "name": "Cricket news from ESPN Cricinfo.com",
                    "url": "https://www.espncricinfo.com/"
                },
                "updated": "2025-08-27T04:55:50"
            },
            {
                "title": "Auguste's 73 off 35 trumps Shepherd's 73* off 34 to lift St Lucia Kings to second",
                "description": "Oshane Thomas concedes 33 runs in a ten-ball over (the 15th of the Amazon Warriors innings) - the most expensive figures by a St Lucia Kings bowler in the CPL",
                "description_text": "Oshane Thomas concedes 33 runs in a ten-ball over (the 15th of the Amazon Warriors innings) - the most expensive figures by a St Lucia Kings bowler in the CPL",
                "image_url": "https://p.imgci.com/db/PICTURES/CMS/405400/405458.6.jpg",
                "link": "https://www.espncricinfo.com/ci/content/story/1500502.html?ex_cid=OTC-RSS",
                "provider": {
                    "name": "Cricket news from ESPN Cricinfo.com",
                    "url": "https://www.espncricinfo.com/"
                },
                "updated": "2025-08-27T04:55:50"
            },
            {
                "title": "Jos Buttler's 70 leaves Northern Superchargers stuck in third",
                "description": "Trent Rockets now in pole position to finish second, which would grant them a Finals spot if the Eliminator is washed out",
                "description_text": "Trent Rockets now in pole position to finish second, which would grant them a Finals spot if the Eliminator is washed out",
                "image_url": "https://p.imgci.com/db/PICTURES/CMS/405400/405456.5.jpg",
                "link": "https://www.espncricinfo.com/ci/content/story/1500495.html?ex_cid=OTC-RSS",
                "provider": {
                    "name": "Cricket news from ESPN Cricinfo.com",
                    "url": "https://www.espncricinfo.com/"
                },
                "updated": "2025-08-26T20:47:26"
            },
            {
                "title": "Jos Buttler's 70 leaves Northern Superchargers stuck in third",
                "description": "Trent Rockets now in pole position to finish second, which would grant them a Finals spot if the Eliminator is washed out",
                "description_text": "Trent Rockets now in pole position to finish second, which would grant them a Finals spot if the Eliminator is washed out",
                "image_url": "https://p.imgci.com/db/PICTURES/CMS/405400/405456.5.jpg",
                "link": "https://www.espncricinfo.com/ci/content/story/1500495.html?ex_cid=OTC-RSS",
                "provider": {
                    "name": "Cricket news from ESPN Cricinfo.com",
                    "url": "https://www.espncricinfo.com/"
                },
                "updated": "2025-08-26T20:47:26"
            }
        ]
    },
    "cache": {
        "key": "api:rz:v5_cricket_news-aggregation",
        "expires": 1756311021.50277,
        "etag": "ET:nY13048344886506557441:0",
        "max_age": 300
    },
    "schema": {
        "major_version": "5.0",
        "minor_version": "2"
    },
    "error": null,
    "http_status_code": 200
}